packageharman/__init__.py
packageharman/topsis.py
packageharman-0.2.dist-info/License.txt.txt
packageharman-0.2.dist-info/METADATA
packageharman-0.2.dist-info/WHEEL
packageharman-0.2.dist-info/top_level.txt
packageharman-0.2.dist-info/RECORD
